LICENSE
MANIFEST.in
Makefile
README.rst
setup.py
pyfuzzer/__init__.py
pyfuzzer/__main__.py
pyfuzzer/pyfuzzer.c
pyfuzzer/pyfuzzer_common.c
pyfuzzer/pyfuzzer_common.h
pyfuzzer/pyfuzzer_print.c
pyfuzzer/version.py
pyfuzzer.egg-info/PKG-INFO
pyfuzzer.egg-info/SOURCES.txt
pyfuzzer.egg-info/dependency_links.txt
pyfuzzer.egg-info/entry_points.txt
pyfuzzer.egg-info/requires.txt
pyfuzzer.egg-info/top_level.txt
pyfuzzer/mutators/__init__.py
pyfuzzer/mutators/generic.py