Metadata-Version: 1.1
Name: pyfuzzer
Version: 0.17.0
Summary: Fuzz test Python modules with libFuzzer.
Home-page: https://github.com/eerimoq/pyfuzzer
Author: Erik Moqvist
Author-email: erik.moqvist@gmail.com
License: MIT
Keywords: fuzz,fuzzying,test
Platform: UNKNOWN
Classifier: License :: OSI Approved :: MIT License
Classifier: Programming Language :: Python :: 3
